converter/__init__.py
converter/main.py
beau_ssi_converter-0.4.0.dist-info/LICENSE
beau_ssi_converter-0.4.0.dist-info/METADATA
beau_ssi_converter-0.4.0.dist-info/WHEEL
beau_ssi_converter-0.4.0.dist-info/top_level.txt
beau_ssi_converter-0.4.0.dist-info/RECORD
