Metadata-Version: 2.1
Name: beau-ssi-converter
Version: 0.4.0
Summary: Automatic Semantic Versioning for Python projects
Home-page: http://github.com/thuongnn/github-actions-learning-python
Author: Nguyen Nhu Thuong
Author-email: thuongnn@ssi.com.vn
License: MIT
Classifier: Programming Language :: Python
Classifier: Programming Language :: Python :: 3
Classifier: Programming Language :: Python :: 3.6
Classifier: Programming Language :: Python :: 3.7
Classifier: Programming Language :: Python :: 3.8
Classifier: Programming Language :: Python :: 3.9
License-File: LICENSE
